shodanx
