Metadata-Version: 2.4
Name: shodanx
Version: 1.1.1
Summary: ShodanX is a terminal-powered recon and OSINT tool built on top of the Shodan Services.
Home-page: https://github.com/RevoltSecurities/ShodanX
Author: D.Sanjai Kumar
Author-email: bughunterz0047@gmail.com
Classifier: Programming Language :: Python :: 3
Classifier: License :: OSI Approved :: MIT License
Classifier: Operating System :: OS Independent
License-File: LICENSE
Requires-Dist: aiodns>=3.2.0
Requires-Dist: aiofiles>=24.1.0
Requires-Dist: appdirs>=1.4.4
Requires-Dist: art>=6.5
Requires-Dist: beautifulsoup4>=4.13.4
Requires-Dist: click>=8.2.0
Requires-Dist: colorama>=0.4.6
Requires-Dist: fake_useragent>=2.0.3
Requires-Dist: httpx>=0.28.1
Requires-Dist: PyYAML>=6.0.2
Requires-Dist: rich>=14.0.0
Requires-Dist: setuptools>=78.1.0
Requires-Dist: lxml>=5.3.2
Requires-Dist: bs4>=0.0.2
Dynamic: author
Dynamic: author-email
Dynamic: classifier
Dynamic: description
Dynamic: description-content-type
Dynamic: home-page
Dynamic: license-file
Dynamic: requires-dist
Dynamic: summary
